render_sdk/__init__.py
render_sdk/client/__init__.py
render_sdk/client/client.py
render_sdk/client/errors.py
render_sdk/client/sse.py
render_sdk/client/tests/__init__.py
render_sdk/client/tests/test_client.py
render_sdk/client/tests/test_sse.py
render_sdk/client/tests/test_util.py
render_sdk/client/types.py
render_sdk/client/util.py
render_sdk/client/workflows.py
render_sdk/public_api/__init__.py
render_sdk/public_api/api/__init__.py
render_sdk/public_api/api/blueprints/__init__.py
render_sdk/public_api/api/blueprints/disconnect_blueprint.py
render_sdk/public_api/api/blueprints/list_blueprint_syncs.py
render_sdk/public_api/api/blueprints/list_blueprints.py
render_sdk/public_api/api/blueprints/retrieve_blueprint.py
render_sdk/public_api/api/blueprints/update_blueprint.py
render_sdk/public_api/api/custom_domains/__init__.py
render_sdk/public_api/api/custom_domains/create_custom_domain.py
render_sdk/public_api/api/custom_domains/delete_custom_domain.py
render_sdk/public_api/api/custom_domains/list_custom_domains.py
render_sdk/public_api/api/custom_domains/refresh_custom_domain.py
render_sdk/public_api/api/custom_domains/retrieve_custom_domain.py
render_sdk/public_api/api/deploys/__init__.py
render_sdk/public_api/api/deploys/cancel_deploy.py
render_sdk/public_api/api/deploys/create_deploy.py
render_sdk/public_api/api/deploys/list_deploys.py
render_sdk/public_api/api/deploys/retrieve_deploy.py
render_sdk/public_api/api/deploys/rollback_deploy.py
render_sdk/public_api/api/disks/__init__.py
render_sdk/public_api/api/disks/add_disk.py
render_sdk/public_api/api/disks/delete_disk.py
render_sdk/public_api/api/disks/list_disks.py
render_sdk/public_api/api/disks/list_snapshots.py
render_sdk/public_api/api/disks/restore_snapshot.py
render_sdk/public_api/api/disks/retrieve_disk.py
render_sdk/public_api/api/disks/update_disk.py
render_sdk/public_api/api/environment_groups/__init__.py
render_sdk/public_api/api/environment_groups/create_env_group.py
render_sdk-0.1.2.dist-info/LICENSE
render_sdk-0.1.2.dist-info/METADATA
render_sdk-0.1.2.dist-info/WHEEL
render_sdk-0.1.2.dist-info/RECORD
