Metadata-Version: 2.3
Name: render_sdk
Version: 0.1.2
Summary: Python SDK for Render Workflows
Author: Render
Author-email: support@render.com
Requires-Python: >=3.10,<4.0
Classifier: Development Status :: 3 - Alpha
Classifier: Intended Audience :: Developers
Classifier: License :: OSI Approved :: Apache Software License
Classifier: Operating System :: OS Independent
Classifier: Programming Language :: Python :: 3
Classifier: Programming Language :: Python :: 3.10
Classifier: Programming Language :: Python :: 3.11
Classifier: Programming Language :: Python :: 3.12
Classifier: Programming Language :: Python :: 3.13
Classifier: Programming Language :: Python :: 3.14
Requires-Dist: aiohttp (>=3.8.0,<4.0.0)
Requires-Dist: httpx (>=0.28.1,<0.29.0)
Requires-Dist: openapi-python-client (>=0.26.1,<0.27.0)
